pyloads/__init__.py
pyloads/aerodynamic_profiles.py
pyloads/blade_data.py
pyloads/operation_dtu10mw.py
pyloads/static_loads.py
pyloads/test_static_loads.py
pyloads_wind_turbine-1.0.3.dist-info/LICENSE.txt
pyloads_wind_turbine-1.0.3.dist-info/METADATA
pyloads_wind_turbine-1.0.3.dist-info/WHEEL
pyloads_wind_turbine-1.0.3.dist-info/top_level.txt
pyloads_wind_turbine-1.0.3.dist-info/RECORD
